pytest_datatest.py
pytest_datatest-0.1.4.dist-info/LICENSE
pytest_datatest-0.1.4.dist-info/METADATA
pytest_datatest-0.1.4.dist-info/WHEEL
pytest_datatest-0.1.4.dist-info/entry_points.txt
pytest_datatest-0.1.4.dist-info/top_level.txt
pytest_datatest-0.1.4.dist-info/RECORD
